MANIFEST.in
setup.py
pile/__init__.py
pile/pile.py
pile.egg-info/PKG-INFO
pile.egg-info/SOURCES.txt
pile.egg-info/dependency_links.txt
pile.egg-info/top_level.txt