Metadata-Version: 1.0
Name: pile
Version: 0.1
Summary: A little client side package management
Home-page: http://wess.github.com/pile
Author: Wess Cope
Author-email: wess@wattz.net
License: MIT
Platform: UNKNOWN
Classifier: Development Status :: 3 - Alpha
Classifier: Intended Audience :: Developers
Classifier: License :: OSI Approved :: MIT License
Classifier: Programming Language :: Python
Classifier: Programming Language :: Python :: 2.6
Classifier: Programming Language :: Python :: 2.7
